geobench_v2/__init__.py
geobench_v2/main.py
geobench_v2/analysis/__init__.py
geobench_v2/analysis/benchmark_tools.py
geobench_v2/analysis/utils.py
geobench_v2/datamodules/__init__.py
geobench_v2/datamodules/base.py
geobench_v2/datamodules/benv2.py
geobench_v2/datamodules/biomassters.py
geobench_v2/datamodules/burn_scars.py
geobench_v2/datamodules/caffe.py
geobench_v2/datamodules/cloudsen12.py
geobench_v2/datamodules/dynamic_earthnet.py
geobench_v2/datamodules/everwatch.py
geobench_v2/datamodules/flair2.py
geobench_v2/datamodules/forestnet.py
geobench_v2/datamodules/fotw.py
geobench_v2/datamodules/kuro_siwo.py
geobench_v2/datamodules/nzcattle.py
geobench_v2/datamodules/pastis.py
geobench_v2/datamodules/pastis_panoptic.py
geobench_v2/datamodules/so2sat.py
geobench_v2/datamodules/spacenet2.py
geobench_v2/datamodules/spacenet6.py
geobench_v2/datamodules/spacenet7.py
geobench_v2/datamodules/spacenet8.py
geobench_v2/datamodules/substation.py
geobench_v2/datamodules/treesatai.py
geobench_v2/datamodules/utils.py
geobench_v2/datasets/__init__.py
geobench_v2/datasets/base.py
geobench_v2/datasets/benv2.py
geobench_v2/datasets/biomassters.py
geobench_v2/datasets/burn_scars.py
geobench_v2/datasets/caffe.py
geobench_v2/datasets/cloudsen12.py
geobench_v2/datasets/data_util.py
geobench_v2/datasets/dynamic_earthnet.py
geobench_v2/datasets/everwatch.py
geobench_v2/datasets/flair2.py
geobench_v2/datasets/forestnet.py
geobench_v2/datasets/fotw.py
geobench_v2/datasets/kuro_siwo.py
geobench_v2/datasets/normalization.py
geobench_v2/datasets/nzcattle.py
geobench_v2/datasets/pastis.py
geobench_v2/datasets/sensor_util.py
geobench_v2/datasets/so2sat.py
geobench_v2/datasets/spacenet2.py
geobench_v2/datasets/spacenet6.py
geobench_v2/datasets/spacenet7.py
geobench_v2/datasets/spacenet8.py
geobench_v2/datasets/substation.py
geobench_v2/datasets/treesatai.py
geobench_v2/datasets/visualization_util.py
geobench_v2/generate_benchmark/__init__.py
geobench_v2/generate_benchmark/benv2.py
geobenchv2-0.9.dist-info/licenses/LICENSE
geobenchv2-0.9.dist-info/METADATA
geobenchv2-0.9.dist-info/WHEEL
geobenchv2-0.9.dist-info/top_level.txt
geobenchv2-0.9.dist-info/RECORD
