Metadata-Version: 2.4
Name: GeoBenchV2
Version: 0.9
Summary: GeoBenchV2: A comprehensive benchmark evaluation suite for Earth observation tasks.
Author-email: Nils Lehmann <n.lehmann@tum.de>, Naomi Simumba <naomi.simumba1@ibm.com>, Paolo Fraccaro <paolo.fraccaro@ibm.com>, Alexandre Lacoste <alexandre.lacoste@servicenow.com>
Maintainer-email: Nils Lehmann <n.lehmann@tum.de>, Naomi Simumba <naomi.simumba1@ibm.com>, Paolo Fraccaro <paolo.fraccaro@ibm.com>, Alexandre Lacoste <alexandre.lacoste@servicenow.com>
License:                                  Apache License
Project-URL: Documentation, https://geo-bench-2.readthedocs.io/en/latest/
Project-URL: Issues, https://github.com/The-AI-Alliance/GEO-Bench-2/issues
Project-URL: Source, https://github.com/The-AI-Alliance/GEO-Bench-2
Keywords: earth observation,benchmark,satellite data,GeoFM
Classifier: Development Status :: 3 - Alpha
Classifier: Intended Audience :: Science/Research
Classifier: License :: OSI Approved :: Apache Software License
Classifier: Operating System :: OS Independent
Classifier: Programming Language :: Python :: 3
Classifier: Programming Language :: Python :: 3.11
Classifier: Programming Language :: Python :: 3.12
Classifier: Programming Language :: Python :: 3.13
Classifier: Topic :: Scientific/Engineering :: Artificial Intelligence
Requires-Python: >=3.11
License-File: LICENSE
Requires-Dist: lightning>=2.3.3
Requires-Dist: matplotlib>=3.5
Requires-Dist: numpy>=1.21.1
Requires-Dist: omegaconf>=2.3.0
Requires-Dist: tacoreader==0.5.6
Requires-Dist: pandas>=1.1.3
Requires-Dist: torch>=2.0
Requires-Dist: torchmetrics>=1.2
Requires-Dist: torchvision>=0.16.1
Requires-Dist: torchgeo>=0.7.1
Requires-Dist: geopandas>=1.1.0
Requires-Dist: h5py>=3.14.0
Requires-Dist: cartopy>=0.25.0
Requires-Dist: scikit-image>=0.25.2
Provides-Extra: tests
Requires-Dist: pytest>=7.3; extra == "tests"
Requires-Dist: pytest-cov>=4; extra == "tests"
Requires-Dist: hydra-core>=1.3.2; extra == "tests"
Requires-Dist: ruff>=0.12.9; extra == "tests"
Provides-Extra: docs
Requires-Dist: sphinx>=4; extra == "docs"
Requires-Dist: ipywidgets>=7; extra == "docs"
Requires-Dist: nbsphinx>=0.8.5; extra == "docs"
Requires-Dist: sphinx-book-theme>=1.0.1; extra == "docs"
Requires-Dist: myst-parser>=2.0; extra == "docs"
Requires-Dist: sphinx-togglebutton>=0.3.2; extra == "docs"
Requires-Dist: jupytext>=1.15.2; extra == "docs"
Requires-Dist: ipykernel>=6.29.3; extra == "docs"
Requires-Dist: pandoc>=2.4; extra == "docs"
Provides-Extra: generate-benchmark
Requires-Dist: scikit-learn==1.7.1; extra == "generate-benchmark"
Requires-Dist: tacotoolbox>=0.5.2; extra == "generate-benchmark"
Requires-Dist: cartopy>=0.25.0; extra == "generate-benchmark"
Requires-Dist: scikit-image>=0.25.2; extra == "generate-benchmark"
Provides-Extra: all
Requires-Dist: GeoBenchV2[docs,generate_benchmark,tests]; extra == "all"
Dynamic: license-file
